{
  "workflow": {
    "unique_name": "definition_workflow_01ffk2GqTvEp0WDikFElXaXp6sZ7w9w3I",
    "name": "RuslanKAFKATEST",
    "title": "RuslanKAFKATEST",
    "type": "generic.workflow",
    "base_type": "workflow",
    "variables": null,
    "properties": {
      "atomic": {
        "is_atomic": false
      },
      "delete_workflow_instance": false,
      "display_name": "RuslanKAFKATEST",
      "favorite": false,
      "target": {
        "target_type": "kafka.endpoint",
        "target_id": "definition_target_01ffKXu2OJTf6SYFpIP1bSmOCNjSBrnl2",
        "execute_on_workflow_target": true
      }
    },
    "object_type": "definition_workflow",
    "actions": [
      {
        "unique_name": "definition_activity_01ffk55cmFNSkaelORuiF1I5yvHgDbBH2",
        "name": "Sleep",
        "title": "Sleep",
        "type": "core.sleep",
        "base_type": "activity",
        "properties": {
          "continue_on_failure": false,
          "display_name": "Sleep",
          "sleep_interval": 1
        },
        "object_type": "definition_activity"
      },
      {
        "unique_name": "definition_activity_01ffWHJSzn9br5RhFQQI5mlMVYx6SeC4m",
        "name": "Submit Kafka Message",
        "title": "Submit Kafka Message",
        "type": "kafka.submitmessage",
        "base_type": "activity",
        "properties": {
          "action_timeout": 180,
          "continue_on_failure": false,
          "display_name": "Submit Kafka Message",
          "message": "11111",
          "runtime_user": {
            "override_target_runtime_user": false,
            "target_default": true
          },
          "target": {
            "override_workflow_target": false,
            "override_workflow_target_group_criteria": false,
            "use_workflow_target": true,
            "use_workflow_target_group": false
          },
          "topic": "my topic"
        },
        "object_type": "definition_activity"
      }
    ],
    "categories": [
      "category_1BMfMXSnJMyt5Ihqi7rWJr5N8cf"
    ]
  },
  "triggers": {
    "triggerevent_01ffkHvqDTzrRIvyIVQQwOolwX0WGIdCb": {
      "workflow_id": "definition_workflow_01ffk2GqTvEp0WDikFElXaXp6sZ7w9w3I",
      "name": "KAFKA TRIGGER",
      "title": "",
      "lowercase_name": "event.kafka_trigger",
      "type": "event",
      "base_type": "trigger",
      "ref_id": "event_01ffKzVosiSGFQ9ebKKuYpdDpo6eqa6aI",
      "version": "1.0.0",
      "disabled": false,
      "unique_name": "triggerevent_01ffkHvqDTzrRIvyIVQQwOolwX0WGIdCb",
      "object_type": "triggerevent"
    }
  },
  "events": {
    "event_01ffKzVosiSGFQ9ebKKuYpdDpo6eqa6aI": {
      "name": "RUSLANKAFKAEVENT",
      "title": "RUSLANKAFKAEVENT",
      "type": "kafka.event",
      "base_type": "event",
      "object_type": "event",
      "target_id": "definition_target_01ffKXu2OJTf6SYFpIP1bSmOCNjSBrnl2",
      "version": "1.0.0",
      "properties": {
        "target_id": "definition_target_01ffKXu2OJTf6SYFpIP1bSmOCNjSBrnl2",
        "title": "RUSLANKAFKAEVENT",
        "topic_name": "mytopic"
      },
      "unique_name": "event_01ffKzVosiSGFQ9ebKKuYpdDpo6eqa6aI"
    }
  },
  "targets": {
    "definition_target_01ffKXu2OJTf6SYFpIP1bSmOCNjSBrnl2": {
      "unique_name": "definition_target_01ffKXu2OJTf6SYFpIP1bSmOCNjSBrnl2",
      "name": "RUSLAN-INTERNALKAFKA",
      "title": "RUSLAN-INTERNALKAFKA",
      "type": "kafka.endpoint",
      "base_type": "target",
      "object_type": "definition_target",
      "properties": {
        "disable_certificate_validation": false,
        "display_name": "RUSLAN-INTERNALKAFKA",
        "host": "10.111.54.53",
        "no_runtime_user": true,
        "port": 9092,
        "ssl_enable": false
      }
    }
  }
}